fillmore/__init__.py
fillmore/libsentry.py
fillmore/pytest_plugin.py
fillmore/scrubber.py
fillmore/test.py
fillmore-2.2.0.dist-info/licenses/LICENSE
fillmore-2.2.0.dist-info/METADATA
fillmore-2.2.0.dist-info/WHEEL
fillmore-2.2.0.dist-info/entry_points.txt
fillmore-2.2.0.dist-info/top_level.txt
fillmore-2.2.0.dist-info/RECORD
