Metadata-Version: 2.4
Name: fillmore
Version: 2.2.0
Summary: Sentry event scrubber and utilities library
Author: Will Kahn-Greene
License: MPLv2
Project-URL: Homepage, https://github.com/mozilla-services/fillmore
Project-URL: Documentation, https://fillmore.readthedocs.io/
Project-URL: Source, https://github.com/mozilla-services/fillmore/
Project-URL: Issues, https://github.com/mozilla-services/fillmore/issues
Keywords: sentry,filter,scrubber
Classifier: Development Status :: 5 - Production/Stable
Classifier: Intended Audience :: Developers
Classifier: License :: OSI Approved :: Mozilla Public License 2.0 (MPL 2.0)
Classifier: Natural Language :: English
Classifier: Operating System :: OS Independent
Classifier: Programming Language :: Python :: 3 :: Only
Classifier: Programming Language :: Python :: 3.10
Classifier: Programming Language :: Python :: 3.11
Classifier: Programming Language :: Python :: 3.12
Classifier: Programming Language :: Python :: 3.13
Classifier: Programming Language :: Python :: 3.14
Classifier: Topic :: Software Development :: Libraries :: Python Modules
Requires-Python: >=3.10
License-File: LICENSE
Requires-Dist: attrs>=21.2.0
Requires-Dist: sentry-sdk>=2
Provides-Extra: dev
Requires-Dist: build; extra == "dev"
Requires-Dist: cogapp; extra == "dev"
Requires-Dist: mypy; extra == "dev"
Requires-Dist: pytest; extra == "dev"
Requires-Dist: ruff; extra == "dev"
Requires-Dist: Sphinx; extra == "dev"
Requires-Dist: sphinx_rtd_theme; extra == "dev"
Requires-Dist: tomli; python_version < "3.11" and extra == "dev"
Requires-Dist: tox; extra == "dev"
Requires-Dist: tox-gh-actions; extra == "dev"
Requires-Dist: tox-uv; extra == "dev"
Requires-Dist: twine; extra == "dev"
Requires-Dist: Werkzeug; extra == "dev"
Dynamic: license-file
